caltopo_python/__init__.py
caltopo_python/caltopo_python.py
caltopo_python-2.0.0.dist-info/licenses/LICENSE
caltopo_python-2.0.0.dist-info/METADATA
caltopo_python-2.0.0.dist-info/WHEEL
caltopo_python-2.0.0.dist-info/top_level.txt
caltopo_python-2.0.0.dist-info/RECORD
