Metadata-Version: 2.4
Name: caltopo_python
Version: 2.0.0
Summary: Python interface to unofficial CalTopo API
Home-page: https://github.com/ncssar/caltopo_python
Download-URL: https://github.com/ncssar/caltopo_python/archive/1.0.0.tar.gz
Author: Tom Grundy
Author-email: nccaves@yahoo.com
Classifier: Programming Language :: Python :: 3
Classifier: License :: OSI Approved :: GNU General Public License v3 (GPLv3)
Classifier: Operating System :: OS Independent
Classifier: Development Status :: 4 - Beta
License-File: LICENSE
Requires-Dist: Shapely>=2.0.2
Requires-Dist: requests
Dynamic: author
Dynamic: author-email
Dynamic: classifier
Dynamic: description
Dynamic: description-content-type
Dynamic: download-url
Dynamic: home-page
Dynamic: license-file
Dynamic: requires-dist
Dynamic: summary
